controlled_vocabulary_fastapi/__init__.py
controlled_vocabulary_fastapi/console_helper.py
controlled_vocabulary_fastapi/constants.py
controlled_vocabulary_fastapi/file_utils.py
controlled_vocabulary_fastapi/system_caller.py
controlled_vocabulary_fastapi-0.1.0.dist-info/AUTHORS.rst
controlled_vocabulary_fastapi-0.1.0.dist-info/METADATA
controlled_vocabulary_fastapi-0.1.0.dist-info/WHEEL
controlled_vocabulary_fastapi-0.1.0.dist-info/entry_points.txt
controlled_vocabulary_fastapi-0.1.0.dist-info/top_level.txt
controlled_vocabulary_fastapi-0.1.0.dist-info/RECORD
