Metadata-Version: 2.2
Name: controlled_vocabulary_fastapi
Version: 0.1.0
Summary: A lightweight REST API implemented using FastAPI for providing read-only endpoints for the controlled vocabulary implemented in the controlled-vocabulary-utils.
Home-page: https://github.com/jai-python3/controlled-vocabulary-fastapi
Author: Jaideep Sundaram
Author-email: jai.python3@gmail.com
Keywords: controlled_vocabulary_fastapi
Classifier: Development Status :: 5 - Production/Stable
Classifier: Intended Audience :: Developers
Classifier: Natural Language :: English
Classifier: Programming Language :: Python :: 3.10
Requires-Python: >=3.10
License-File: AUTHORS.rst
Requires-Dist: Click>=7.0
Requires-Dist: PyYAML
Requires-Dist: Rich
Dynamic: author
Dynamic: author-email
Dynamic: classifier
Dynamic: description
Dynamic: description-content-type
Dynamic: home-page
Dynamic: keywords
Dynamic: requires-dist
Dynamic: requires-python
Dynamic: summary
